npbackup/__debug__.py
npbackup/__env__.py
npbackup/__init__.py
npbackup/__main__.py
npbackup/__version__.py
npbackup/common.py
npbackup/configuration.py
npbackup/key_management.py
npbackup/obfuscation.py
npbackup/path_helper.py
npbackup/pidfile_ng.py
npbackup/runner_interface.py
npbackup/secret_keys.py
npbackup/task.py
npbackup/core/__init__.py
npbackup/core/i18n_helper.py
npbackup/core/jobs.py
npbackup/core/metrics.py
npbackup/core/nuitka_helper.py
npbackup/core/restic_source_binary.py
npbackup/core/runner.py
npbackup/core/upgrade_runner.py
npbackup/gui/__init__.py
npbackup/gui/__main__.py
npbackup/gui/config.py
npbackup/gui/constants.py
npbackup/gui/handle_window.py
npbackup/gui/helpers.py
npbackup/gui/operations.py
npbackup/gui/skinner.py
npbackup/gui/viewer.py
npbackup/gui/wizard.py
npbackup/restic_metrics/__init__.py
npbackup/restic_wrapper/__init__.py
npbackup/restic_wrapper/schema.py
npbackup/translations/config_gui.en.yml
npbackup/translations/config_gui.fr.yml
npbackup/translations/generic.en.yml
npbackup/translations/generic.fr.yml
npbackup/translations/main_gui.en.yml
npbackup/translations/main_gui.fr.yml
npbackup/translations/operations_gui.en.yml
npbackup/translations/operations_gui.fr.yml
npbackup/translations/wizard_gui.en.yml
npbackup/translations/wizard_gui.fr.yml
npbackup/upgrade_client/__init__.py
npbackup/upgrade_client/upgrader.py
npbackup-3.0.4.data/scripts/npbackup-cli.cmd
resources/__init__.py
resources/customization.py
resources/update_custom_resources.py
npbackup-3.0.4.dist-info/LICENSE
npbackup-3.0.4.dist-info/METADATA
npbackup-3.0.4.dist-info/WHEEL
npbackup-3.0.4.dist-info/entry_points.txt
npbackup-3.0.4.dist-info/top_level.txt
npbackup-3.0.4.dist-info/RECORD
