Metadata-Version: 2.1
Name: npbackup
Version: 3.0.4
Summary: One fits all solution for deduplicated and compressed backups on servers and laptops
Home-page: https://github.com/netinvent/npbackup
Author: NetInvent - Orsiris de Jong
Author-email: contact@netinvent.fr
License: GPLv3
Keywords: shell,backup,deduplication,compression,prometheus,windows,linux,gui,cli,restic,viewer,kvm,qemu,grafana,vss
Classifier: Development Status :: 5 - Production/Stable
Classifier: Intended Audience :: End Users/Desktop
Classifier: Intended Audience :: System Administrators
Classifier: Intended Audience :: Information Technology
Classifier: Intended Audience :: Developers
Classifier: Intended Audience :: Science/Research
Classifier: Topic :: System :: Archiving :: Backup
Classifier: Topic :: System
Classifier: Topic :: System :: Monitoring
Classifier: Topic :: Utilities
Classifier: Programming Language :: Python
Classifier: Programming Language :: Python :: 3
Classifier: Programming Language :: Python :: 3.6
Classifier: Programming Language :: Python :: 3.7
Classifier: Programming Language :: Python :: 3.8
Classifier: Programming Language :: Python :: 3.9
Classifier: Programming Language :: Python :: 3.10
Classifier: Programming Language :: Python :: 3.11
Classifier: Programming Language :: Python :: Implementation :: CPython
Classifier: Programming Language :: Python :: Implementation :: PyPy
Classifier: Operating System :: POSIX :: Linux
Classifier: Operating System :: Microsoft :: Windows
Classifier: License :: OSI Approved :: GNU General Public License v3 (GPLv3)
Requires-Python: >=3.6
License-File: LICENSE
Requires-Dist: command-runner >=1.7.5
Requires-Dist: cryptidy >=1.2.4
Requires-Dist: python-dateutil
Requires-Dist: ofunctions.logger-utils >=2.5.0
Requires-Dist: ofunctions.misc >=1.8.0
Requires-Dist: ofunctions.process >=2.1.0
Requires-Dist: ofunctions.threading >=2.2.0
Requires-Dist: ofunctions.platform >=1.5.5
Requires-Dist: ofunctions.random
Requires-Dist: ofunctions.requestor >=1.2.2
Requires-Dist: ofunctions.mailer >=1.3.0
Requires-Dist: freesimplegui ==5.2.0
Requires-Dist: requests
Requires-Dist: ruamel.yaml
Requires-Dist: psutil
Requires-Dist: pyyaml
Requires-Dist: i18nice >=0.6.2
Requires-Dist: packaging
Requires-Dist: ntplib >=0.4.0
Requires-Dist: imageio ; platform_system == "Darwin"
Requires-Dist: pywin32 ; platform_system == "Windows"
